src/__init__.py
src/cli.py
src/config.py
src/main.py
src/apps/__init__.py
src/apps/events.py
src/apps/handlers.py
src/apps/jobs.py
src/apps/server.py
src/apps/authentication/__init__.py
src/apps/authentication/exceptions.py
src/apps/authentication/controllers/__init__.py
src/apps/authentication/controllers/auth.py
src/apps/authentication/models/__init__.py
src/apps/authentication/models/authentication.py
src/apps/authentication/schemas/__init__.py
src/apps/authentication/schemas/request.py
src/apps/authentication/schemas/response.py
src/apps/authentication/services/__init__.py
src/apps/authentication/services/auth.py
src/constants/__init__.py
src/constants/messages.py
authentication_microservices_webelight-0.0.1.dist-info/LICENSE.txt
authentication_microservices_webelight-0.0.1.dist-info/METADATA
authentication_microservices_webelight-0.0.1.dist-info/WHEEL
authentication_microservices_webelight-0.0.1.dist-info/top_level.txt
authentication_microservices_webelight-0.0.1.dist-info/RECORD
