Metadata-Version: 2.1
Name: authentication_microservices_webelight
Version: 0.0.1
Summary: Authentication Microservices
Author: Keyur Parmar
Author-email: keyurp@webelight.co.in
License-File: LICENSE.txt
